{
  "x": [
    {
      "timestamp": 0,
      "value": 0
    },
    {
      "timestamp": 3,
      "value": -2000
    },
    {
      "timestamp": 5,
      "value": -1560
    },
    {
      "timestamp": 17,
      "value": 1790
    },
    {
      "timestamp": 30,
      "value": 66
    },
    {
      "timestamp": 42,
      "value": -66
    },
    {
      "timestamp": 50,
      "value": 1852
    },
    {
      "timestamp": 62,
      "value": 2418
    },
    {
      "timestamp": 85,
      "value": 0
    }
  ],
  "y": [
    {
      "timestamp": 0,
      "value": 0
    },
    {
      "timestamp": 3,
      "value": 0
    },
    {
      "timestamp": 5,
      "value": 2109
    },
    {
      "timestamp": 17,
      "value": -1345
    },
    {
      "timestamp": 30,
      "value": -76
    },
    {
      "timestamp": 42,
      "value": 122
    },
    {
      "timestamp": 50,
      "value": -610
    },
    {
      "timestamp": 62,
      "value": 2609
    },
    {
      "timestamp": 85,
      "value": 0
    }
  ],
  "z": [
    {
      "timestamp": 0,
      "value": 0
    },
    {
      "timestamp": 3,
      "value": 0
    },
    {
      "timestamp": 5,
      "value": 0
    },
    {
      "timestamp": 17,
      "value": 0
    },
    {
      "timestamp": 30,
      "value": 0
    },
    {
      "timestamp": 42,
      "value": 0
    },
    {
      "timestamp": 50,
      "value": 0
    },
    {
      "timestamp": 62,
      "value": 0
    },
    {
      "timestamp": 85,
      "value": 0
    }
  ]
}
